{
  "timestamp": "2023-12-19T08:14:50",
  "url": "https://www.gmx.net/",
  "response": {
    "status": 200
  },
  "scripts": [
    {
      "type": null,
      "src": "https://s.uicdn.com/t/prod/iq/mam/purple/daq.js",
      "id": null,
      "text": null
    },
    {
      "type": null,
      "src": "https://dl.gmx.net/tcf/live/v1/js/tcf-api.js",
      "id": null,
      "text": null
    },
    {
      "type": null,
      "src": "https://img.ui-portal.de/pos-cdn/tracklib/4.7.3/tracklib.poly.min.js",
      "id": null,
      "text": null
    },
    {
      "type": null,
      "src": "https://js.ui-portal.de/homepage/res/legacy/live/1.50/gmx/js/piNctTracking.js",
      "id": null,
      "text": null
    },
    {
      "type": null,
      "src": "https://js.ui-portal.de/homepage/res/legacy/live/1.50/gmx/chunk-vendors.bundle.js",
      "id": null,
      "text": null
    },
    {
      "type": null,
      "src": "https://js.ui-portal.de/homepage/res/legacy/live/1.50/gmx/chunk-common.bundle.js",
      "id": null,
      "text": null
    },
    {
      "type": null,
      "src": "https://js.ui-portal.de/homepage/res/legacy/live/1.50/gmx/homepage.bundle.js",
      "id": null,
      "text": null
    }
  ],
  "articles": [
    {
      "title": "Vulkan auf Island ausgebrochen - Notfallstufe ausgerufen",
      "url": "https://www.gmx.net/magazine/panorama/vulkanausbruch-island-38983328",
      "image_url": "https://i0.gmx.net/image/726/38983726,pd=1,h=300,w=530.jpg"
    },
    {
      "title": "Selenskyj äußert sich zu neuem Sanktionspaket gegen Russland",
      "url": "https://www.gmx.net/magazine/politik/russland-krieg-ukraine/kiew-begruesst-eu-sanktionen-moskau-lage-ueberblick-38983486",
      "image_url": "https://i0.gmx.net/image/606/38983606,pd=5,h=300,w=530.jpg"
    },
    {
      "title": "Suche nach vermisster Zweijähriger geht weiter - Spürhunde schlagen an",
      "url": "https://www.gmx.net/magazine/panorama/suche-vermisster-zweijaehriger-spuerhunde-schlagen-38983580",
      "image_url": "https://i0.gmx.net/image/784/38983784,pd=2,h=300,w=530.jpg"
    },
    {
      "title": "Riesiger Rückruf von veganen Produkten bei Edeka",
      "url": "https://www.gmx.net/magazine/ratgeber/finanzen-verbraucher/aktuelle-rueckrufe-edek-eigenmarke-ruft-vegane-produkte-zurueck-38909024",
      "image_url": "https://i0.gmx.net/image/896/38980896,pd=2,h=300,w=530/fahnen-edeka-logo.jpg",
      "image_title": "Fahnen mit Edeka-Logo"
    },
    {
      "title": "Sorge um Gundula Gause: \"heute journal\"-Moderation abgebrochen",
      "url": "https://www.gmx.net/magazine/unterhaltung/tv-shows/sorge-gundula-gause-journal-moderation-abgebrochen-38983432",
      "image_url": "https://i0.gmx.net/image/464/38983464,pd=4,h=300,w=530/gundula-gause.jpg",
      "image_title": "Gundula Gause."
    },
    {
      "title": "Tote und Verletzte nach Erdbeben in China",
      "url": "https://www.gmx.net/magazine/panorama/118-tote-erdbeben-nordwesten-chinas-38983332"
    },
    {
      "title": "Tabellenführung verloren! Was ist los mit den Bayern?",
      "url": "https://www.gmx.net/magazine/sport/fussball/bundesliga/fc-bayern-schwaechelt-wolfsburg-zittert-spitze-38983770"
    },
    {
      "title": "Amira und Oliver Pocher: Streit vor ZDF-Spendenshow \"Ein Herz für Kinder\"",
      "url": "https://www.gmx.net/magazine/unterhaltung/stars/amira-pocher-ex-auto-38983498"
    },
    {
      "title": "Muss Berlin noch einmal wählen? Verfassungsgericht urteilt zur Pannenwahl",
      "url": "https://www.gmx.net/magazine/politik/wahlen/bundestagswahl/berlin-waehlen-verfassungsgericht-urteilt-pannenwahl-38983922"
    },
    {
      "title": "Bizarrer TV-Moment: Empfiehlt sich Silbereisen hier schon für das Dschungelcamp?",
      "url": "https://www.gmx.net/magazine/unterhaltung/tv-shows/adventsparty-florian-silbereisen-endlich-mehlwuermer-essen-atomkraftwerk-basteln-38983496",
      "image_url": "https://i0.gmx.net/image/570/38983570,pd=1,h=170,w=300.jpg"
    },
    {
      "title": "Herzogin Kate begeistert mit Foto aus ihrer Kindheit",
      "url": "https://www.gmx.net/magazine/unterhaltung/adel/britische-royals/herzogin-kate-gewaehrt-einblick-kindheit-38983722",
      "image_url": "https://i0.gmx.net/image/736/38983736,pd=1,h=170,w=300/herzogin-kate.jpg",
      "image_title": "Herzogin Kate."
    },
    {
      "title": "Eishockey-Prügelei sorgt für Aufsehen: Was hinter solchen Aktionen steckt",
      "url": "https://www.gmx.net/magazine/sport/eishockey/schlaegereien-eishockey-folklore-bad-guys-wayne-gretzkys-polizei-38982378",
      "image_url": "https://i0.gmx.net/image/492/38982492,pd=1,h=170,w=300.jpg"
    },
    {
      "title": "Babyglück bei Prinzessin Alexandra von Luxemburg und Nicolas Bagory",
      "url": "https://www.gmx.net/magazine/unterhaltung/adel/babyglueck-prinzessin-alexandra-luxemburg-nicolas-bagory-38983470"
    },
    {
      "title": "Emotionale Worte: Kylie Minogue spricht über ihr Brustkrebs-Trauma",
      "url": "https://www.gmx.net/magazine/unterhaltung/stars/kylie-minogue-kaempft-18-jahre-krebsdiagnose-trauma-38983572"
    },
    {
      "title": "Zwei Tote nach Brand in Stadtklinik Frankenthal gefunden",
      "url": "https://www.gmx.net/magazine/panorama/brand-pfaelzischem-krankenhaus-tote-gefunden-38983266"
    },
    {
      "title": "US-Schauspieler James McCaffrey gestorben",
      "url": "https://www.gmx.net/magazine/unterhaltung/stars/us-schauspieler-james-mccaffrey-gestorben-38983424"
    },
    {
      "title": "Die schönsten Weihnachtsfilme aller Zeiten",
      "url": "https://www.gmx.net/magazine/unterhaltung/filme-serien-kino/schoensten-weihnachtsfilme-zeiten-38974568",
      "image_url": "https://i0.gmx.net/image/574/38974574,pd=1,h=170,w=300.jpg"
    },
    {
      "title": "Tote und Verletzte nach Erdbeben in China",
      "url": "https://www.gmx.net/magazine/panorama/118-tote-erdbeben-nordwesten-chinas-38983332",
      "image_url": "https://i0.gmx.net/image/742/38983742,pd=1,h=170,w=300.jpg"
    },
    {
      "title": "Tabellenführung verloren! Was ist los mit den Bayern?",
      "url": "https://www.gmx.net/magazine/sport/fussball/bundesliga/fc-bayern-schwaechelt-wolfsburg-zittert-spitze-38983770"
    },
    {
      "title": "Amira und Oliver Pocher: Streit vor ZDF-Spendenshow \"Ein Herz für Kinder\"",
      "url": "https://www.gmx.net/magazine/unterhaltung/stars/amira-pocher-ex-auto-38983498"
    },
    {
      "title": "Muss Berlin noch einmal wählen? Verfassungsgericht urteilt zur Pannenwahl",
      "url": "https://www.gmx.net/magazine/politik/wahlen/bundestagswahl/berlin-waehlen-verfassungsgericht-urteilt-pannenwahl-38983922"
    },
    {
      "title": "Herzogin Kate begeistert mit Foto aus ihrer Kindheit",
      "url": "https://www.gmx.net/magazine/unterhaltung/adel/britische-royals/herzogin-kate-gewaehrt-einblick-kindheit-38983722"
    },
    {
      "title": "Eishockey-Prügelei sorgt für Aufsehen: Was hinter solchen Aktionen steckt",
      "url": "https://www.gmx.net/magazine/sport/eishockey/schlaegereien-eishockey-folklore-bad-guys-wayne-gretzkys-polizei-38982378",
      "image_url": "https://i0.gmx.net/image/492/38982492,pd=1,h=170,w=300.jpg"
    },
    {
      "title": "Bizarrer TV-Moment: Empfiehlt sich Silbereisen hier schon für das Dschungelcamp?",
      "url": "https://www.gmx.net/magazine/unterhaltung/tv-shows/adventsparty-florian-silbereisen-endlich-mehlwuermer-essen-atomkraftwerk-basteln-38983496",
      "image_url": "https://i0.gmx.net/image/570/38983570,pd=1,h=170,w=300.jpg"
    },
    {
      "title": "Tote und Verletzte nach Erdbeben in China",
      "url": "https://www.gmx.net/magazine/panorama/118-tote-erdbeben-nordwesten-chinas-38983332"
    },
    {
      "title": "Tabellenführung verloren! Was ist los mit den Bayern?",
      "url": "https://www.gmx.net/magazine/sport/fussball/bundesliga/fc-bayern-schwaechelt-wolfsburg-zittert-spitze-38983770"
    },
    {
      "title": "Amira und Oliver Pocher: Streit vor ZDF-Spendenshow \"Ein Herz für Kinder\"",
      "url": "https://www.gmx.net/magazine/unterhaltung/stars/amira-pocher-ex-auto-38983498"
    },
    {
      "title": "Muss Berlin noch einmal wählen? Verfassungsgericht urteilt zur Pannenwahl",
      "url": "https://www.gmx.net/magazine/politik/wahlen/bundestagswahl/berlin-waehlen-verfassungsgericht-urteilt-pannenwahl-38983922"
    },
    {
      "title": "Hilfe & Kontakt",
      "teaser": "Hilfestellung & Anleitung zu Ihrem GMX E-Mail Konto",
      "url": "https://hilfe.gmx.net/",
      "image_url": "https://i0.gmx.net/image/518/34288518,pd=2,h=80,w=80.svg"
    },
    {
      "title": "Kundencenter",
      "teaser": "Ihre Daten und Sicherheits-Einstellungen verwalten",
      "url": "https://account.gmx.net/#.pc_page.homepage.index.footer_2.kundencenter",
      "image_url": "https://i0.gmx.net/image/512/34288512,pd=2,h=80,w=80.svg"
    },
    {
      "title": "Passwort vergessen",
      "teaser": "Ihr Passwort zurücksetzen und ein neues anlegen",
      "url": "https://passwort.gmx.net/",
      "image_url": "https://i0.gmx.net/image/522/34288522,pd=2,h=80,w=80.svg"
    },
    {
      "title": "Privatsphäre",
      "teaser": "Alle Informationen zum Datenschutz bei GMX",
      "url": "https://www.gmx.net/datenschutz/#.pc_page.homepage.index.footer_4.datenschutz",
      "image_url": "https://i0.gmx.net/image/524/34288524,pd=2,h=80,w=80.svg"
    },
    {
      "title": "Tote und Verletzte nach Erdbeben in China",
      "url": "https://www.gmx.net/magazine/panorama/118-tote-erdbeben-nordwesten-chinas-38983332",
      "image_url": "https://i0.gmx.net/image/742/38983742,pd=1,h=170,w=300.jpg"
    },
    {
      "title": "Tabellenführung verloren! Was ist los mit den Bayern?",
      "url": "https://www.gmx.net/magazine/sport/fussball/bundesliga/fc-bayern-schwaechelt-wolfsburg-zittert-spitze-38983770"
    },
    {
      "title": "Amira und Oliver Pocher: Streit vor ZDF-Spendenshow \"Ein Herz für Kinder\"",
      "url": "https://www.gmx.net/magazine/unterhaltung/stars/amira-pocher-ex-auto-38983498"
    },
    {
      "title": "Muss Berlin noch einmal wählen? Verfassungsgericht urteilt zur Pannenwahl",
      "url": "https://www.gmx.net/magazine/politik/wahlen/bundestagswahl/berlin-waehlen-verfassungsgericht-urteilt-pannenwahl-38983922"
    },
    {
      "title": "Herzogin Kate begeistert mit Foto aus ihrer Kindheit",
      "url": "https://www.gmx.net/magazine/unterhaltung/adel/britische-royals/herzogin-kate-gewaehrt-einblick-kindheit-38983722"
    }
  ]
}