{
  "timestamp": "2023-11-23T09:11:56",
  "url": "https://www.bild.de/ratgeber/startseite/ratgeber/home-15478376.bild.html",
  "response": {
    "status": 200
  },
  "scripts": [
    {
      "type": null,
      "src": "https://cmp2.bild.de/wrapperMessagingWithoutDetection.js",
      "id": null,
      "text": null
    },
    {
      "type": null,
      "src": "https://www.asadcdn.com/adlib/pages/bild.js",
      "id": null,
      "text": null
    },
    {
      "type": null,
      "src": "https://rosetta.prod.ps.bild.de/ps-rosetta.js",
      "id": null,
      "text": null
    },
    {
      "type": null,
      "src": "https://ast.bild.de/bild-bild.de/prod/utag.js",
      "id": null,
      "text": null
    },
    {
      "type": null,
      "src": "https://data-bb21a2f11b.bild.de/iomm/latest/bootstrap/loader.js",
      "id": null,
      "text": null
    },
    {
      "type": null,
      "src": "https://a.bildstatic.de/runtime.9f14b2c8.js",
      "id": null,
      "text": null
    },
    {
      "type": null,
      "src": "https://a.bildstatic.de/pages/_.f9fcbae0.js",
      "id": null,
      "text": null
    },
    {
      "type": null,
      "src": "https://a.bildstatic.de/commons/pages/_.0b84de44.js",
      "id": null,
      "text": null
    },
    {
      "type": null,
      "src": "https://a.bildstatic.de/commons/app.231d6f3e.js",
      "id": null,
      "text": null
    },
    {
      "type": null,
      "src": "https://a.bildstatic.de/app.2662c407.js",
      "id": null,
      "text": null
    }
  ],
  "articles": [
    {
      "title": "Polizei sucht Kapuzen-Mann Bar-Gäste homophob beleidigt und attackiert",
      "url": "https://www.bild.de/regional/berlin/berlin-aktuell/berlin-bar-gaeste-homophob-beleidigt-und-mit-reizgas-attackiert-86191738.bild.html"
    },
    {
      "title": "Angebliche Vorteile auf dem Prüfstand Zahlen Beamte wirklich weniger Kfz-Versicherung?",
      "url": "https://www.bild.de/bild-plus/ratgeber/leben-und-wissen-verbraucherportal/verbraucherportal/kfz-versicherung-rabatt-mythen-beim-wechsel-im-check-86156264.bild.html"
    },
    {
      "title": "Tief in der Erde Unter ihrem Haus ist ein Geheimnis",
      "url": "https://www.bild.de/video/clip/video/zwei-stockwerke-tief-frau-buddelt-sich-bunker-86155142.bild.html"
    }
  ]
}